odoo10_addon_purchase_comment_template-10.0.1.0.0.99.dev4-nspkg.pth
odoo/addons/purchase_comment_template/README.rst
odoo/addons/purchase_comment_template/__init__.py
odoo/addons/purchase_comment_template/__manifest__.py
odoo/addons/purchase_comment_template/i18n/ca.po
odoo/addons/purchase_comment_template/i18n/fr.po
odoo/addons/purchase_comment_template/i18n/purchase_comment_template.pot
odoo/addons/purchase_comment_template/models/__init__.py
odoo/addons/purchase_comment_template/models/purchase_order.py
odoo/addons/purchase_comment_template/security/ir.model.access.csv
odoo/addons/purchase_comment_template/static/description/icon.png
odoo/addons/purchase_comment_template/static/src/css/purchase.css
odoo/addons/purchase_comment_template/tests/__init__.py
odoo/addons/purchase_comment_template/tests/test_purchase_order_report.py
odoo/addons/purchase_comment_template/views/base_comment_template_view.xml
odoo/addons/purchase_comment_template/views/purchase_order_view.xml
odoo/addons/purchase_comment_template/views/report_purchaseorder.xml
odoo/addons/purchase_comment_template/views/report_quotation.xml
odoo10_addon_purchase_comment_template-10.0.1.0.0.99.dev4.dist-info/METADATA
odoo10_addon_purchase_comment_template-10.0.1.0.0.99.dev4.dist-info/WHEEL
odoo10_addon_purchase_comment_template-10.0.1.0.0.99.dev4.dist-info/namespace_packages.txt
odoo10_addon_purchase_comment_template-10.0.1.0.0.99.dev4.dist-info/top_level.txt
odoo10_addon_purchase_comment_template-10.0.1.0.0.99.dev4.dist-info/RECORD
